README.md
setup.cfg
setup.py
getjobs/__init__.py
getjobs/getjob.py
getjobs.egg-info/PKG-INFO
getjobs.egg-info/SOURCES.txt
getjobs.egg-info/dependency_links.txt
getjobs.egg-info/top_level.txt