Metadata-Version: 2.1
Name: getjobs
Version: 1.1
Summary: UNKNOWN
Home-page: https://github.com/ronaldsoft/getjob
Author: Ronald Rivera
Author-email: ronaldsoft8423@gmail.com
License: GNUv3.0
Keywords: jobs,work,recruiter
Platform: UNKNOWN
Classifier: Development Status :: 5 - Production/Stable
Classifier: Intended Audience :: Developers
Classifier: Topic :: Software Development :: Build Tools
Classifier: License :: OSI Approved :: GNU General Public License v3 or later (GPLv3+)
Classifier: Programming Language :: Python :: 2.7
Classifier: Programming Language :: Python :: 3
Classifier: Programming Language :: Python :: 3.4
Classifier: Programming Language :: Python :: 3.5
Classifier: Programming Language :: Python :: 3.6
